[{"name":"3310","description":"somthing longer","brand":"iphone","imageUrl":"https://drop.ndtv.com/TECH/product_database/images/2152017124957PM_635_nokia_3310.jpeg?downsize=*:420&output-quality=80","price":100,"category":"smartphones","updatedAt":"2021-10-25T09:31:52.000Z"},{"name":"tablet","description":"somthing very longer","brand":"samsung","imageUrl":"https://drop.ndtv.com/TECH/product_database/images/2152017124957PM_635_nokia_3310.jpeg?downsize=*:420&output-quality=80","price":100,"category":"smartphones","updatedAt":"2021-10-25T09:59:01.756Z"},{"name":"lamp","description":"somthing very longer","brand":"samsung","imageUrl":"https://drop.ndtv.com/TECH/product_database/images/2152017124957PM_635_nokia_3310.jpeg?downsize=*:420&output-quality=80","price":100,"category":"smartphones","id":"3dv7jdd9gkv6hro1g","createdAt":"2021-10-25T10:02:37.657Z","updatedAt":"2021-10-25T10:04:56.730Z"},{"name":"3310","description":"somthing longer","brand":"nokia","imageUrl":"https://drop.ndtv.com/TECH/product_database/images/2152017124957PM_635_nokia_3310.jpeg?downsize=*:420&output-quality=80","price":100,"category":"smartphones","id":"3dv7jddn0kv6uebva","createdAt":"2021-10-25T15:56:28.437Z"}]
